Workbook

Sheet README
A1: Reversal & Trend-Following Trading Strategy — Template v0.1
A3: PURPOSE
A4: This workbook is the editable specification for James's stock-trading strategy.
A5: Edit the YELLOW cells. They feed every calculation downstream.
A6: Once finalized, hand this and the paired markdown spec to Claude Code to build the engine.
A8: CORE PRINCIPLE
A9: Identify reversal signals. Trade in the direction of confirmed momentum. Never trade against momentum.
A11: HOW IT WORKS
A12: 1. Each component (candlestick, pivots, volume, EMA, S/R, MACD, RSI) outputs a sub-score from -100 to +100.
A13: 2. Each component has a weight. All weights sum to 100.
A14: 3. Composite score = sum of (sub-score × weight / 100). Range: -100 to +100.
A15: 4. Before computing, a Regime Filter gates long or short signals (prevents counter-trend trades).
... A51: but must be resolved before live trading.

Sheet Strategy_Config
A1: COMPONENT WEIGHTS (must sum to 100)
A2: # | B2: Component | C2: Weight | D2: Notes
A3: 1 | B3: Candlestick pattern | C3: 12 | D3: Current-bar pattern
A4: 2 | B4: P3 Pivot | C4: 8 | D4: 3-bar structure
A5: 3 | B5: P5 Pivot | C5: 12 | D5: 5-bar structure (more reliable than P3)
A6: 4 | B6: Volume (contextual) | C6: 10 | D6: Conditional on price direction
A7: 5 | B7: EMA system | C7: 15 | D7: 20/50/100/200 EMAs
A8: 6 | B8: Support / Resistance | C8: 15 | D8: Bounce vs break
A9: 7 | B9: MACD | C9: 18 | D9: Includes divergence
A10: 8 | B10: RSI | C10: 10 | D10: Excludes divergence (handled in MACD)
B11: TOTAL | C11: =SUM(C3:C10) -> 100 | D11: Must equal 100
B12: Validation: | C12: =IF(C11=100,"OK","FIX: total must be 100") -> OK
A15: SIGNAL THRESHOLDS
A16: Signal | B16: Lower bound | C16: Upper bound | D16: Notes
A17: Strong Buy | B17: 85 | C17: 100 | D17: High-conviction long entry
A18: Buy | B18: 70 | C18: 85 | D18: Standard long entry
A19: Hold | B19: -70 | C19: 70 | D19: No action
A20: Sell | B20: -85 | C20: -70 | D20: Standard short / exit long
A21: Strong Sell | B21: -100 | C21: -85 | D21: High-conviction short / exit long

Sheet Regime_Filter
A1: REGIME FILTER — Pre-score gate (enforces 'never trade against momentum')
A2: Before computing composite score, evaluate this gate. If a side fails, that side's score is clamped to 0. EMA200 slope = sign of (EMA200 today − EMA200 20 bars ago).
A4: Regime Condition | B4: Long allowed? | C4: Short allowed? | D4: Notes
A5: Price > EMA200 AND EMA200 slope ≥ 0 | B5: Yes | C5: No | D5: Bull regime — long-only or reduced-weight shorts
A6: Price < EMA200 AND EMA200 slope ≤ 0 | B6: No | C6: Yes | D6: Bear regime — short-only or reduced-weight longs
A7: Mixed (price one side, slope the other) OR EMA200 flat | B7: Yes | C7: Yes | D7: Range / transition — both sides allowed

Sheet Candlestick
A1: CANDLESTICK PATTERN SCORING (weight: 12)
A2: Pattern | B2: Definition | C2: Sub-score (-100 to +100) | D2: Notes
A3: Long Bullish Candle | B3: Body ≥ 70% of range; close > open; large total range | C3: 90 | D3: Strong bullish momentum bar
A4: Green Hammer | B4: Green body in upper 1/3; lower wick ≥ 2× body | C4: 80 | D4: Classic bullish reversal
A5: Inverted Green Hammer | B5: Green body in lower 1/3; upper wick ≥ 2× body | C5: 55 | D5: Moderate bullish reversal
A6: Bullish Spinning Top | B6: Small green body centered; wicks both sides | C6: 25 | D6: Mild indecision, slight bull bias
A7: Bullish Doji | B7: Open ≈ close (within 5% of range); at recent low | C7: 20 | D7: Indecision at low — possible reversal
A8: No clear pattern | B8: — | C8: 0 | D8: No bar-level signal
A9: Bearish Doji | B9: Open ≈ close; at recent high | C9: -20 | D9: Indecision at high — possible reversal
A10: Bearish Spinning Top | B10: Small red body centered; wicks both sides | C10: -25 | D10: Mild indecision, slight bear bias
A11: Red Hammer (Hanging Man) | B11: Red body in upper 1/3; lower wick ≥ 2× body | C11: -55 | D11: Hanging man pattern
A12: Inverted Red Hammer (Shooting Star) | B12: Red body in lower 1/3; upper wick ≥ 2× body | C12: -80 | D12: Classic bearish reversal
A13: Long Bearish Candle | B13: Body ≥ 70% of range; close < open; large range | C13: -90 | D13: Strong bearish momentum bar
A15: CONTEXT MULTIPLIER (optional)
A16: Condition | B16: Multiplier | C16: Cap | D16: Notes
A17: Pattern occurs AT P5 pivot support/resistance level | B17: 1.2 | C17: ±100 | D17: Strengthens reversal patterns at key levels

Sheet Pivots_P3_P5
A1: P3 PIVOT (weight: 8) — 3-bar window including current
A2: P3 Pattern | B2: Definition | C2: Sub-score | D2: Notes
A3: Bullish reversal at support | B3: Clear 3-bar low; current bar closes above prior 2; lower wicks on bars 1–2 | C3: 70 | D3: Strong reversal signal
A4: Bullish breakout above resistance | B4: Current bar closes above high of prior 2 AND above known resistance | C4: 60 | D4: Trend continuation / breakout
A5: Continuation up | B5: All 3 bars closing progressively higher | C5: 30 | D5: Trend in motion
A6: No clear pattern | B6: — | C6: 0 | D6: No structural signal
A7: Continuation down | B7: All 3 bars closing progressively lower | C7: -30 | D7: Bearish trend in motion
A8: Bearish breakdown below support | B8: Current bar closes below low of prior 2 AND below support | C8: -60 | D8: Trend continuation / breakdown
A9: Bearish reversal at resistance | B9: Clear 3-bar high; current closes below prior 2; upper wicks on bars 1–2 | C9: -70 | D9: Strong reversal signal
A12: P5 PIVOT (weight: 12) — 5-bar window including current
A13: P5 Pattern | B13: Definition | C13: Sub-score | D13: Notes
A14: Major bullish reversal | B14: Clear 5-bar low; current bar closes higher; volume confirmation | C14: 85 | D14: High-conviction reversal
A15: Bullish trend confirmation | B15: 5-bar window shows Higher Highs + Higher Lows | C15: 50 | D15: Healthy uptrend
A16: Range-bound | B16: No clear directional structure across 5 bars | C16: 0 | D16: No actionable signal
A17: Bearish trend confirmation | B17: 5-bar window shows Lower Highs + Lower Lows | C17: -50 | D17: Healthy downtrend
A18: Major bearish reversal | B18: Clear 5-bar high; current bar closes lower; volume confirmation | C18: -85 | D18: High-conviction reversal

Sheet Volume
A1: VOLUME — CONTEXTUAL SCORING (weight: 10)
A2: Volume itself has no direction. Score depends on the price-direction of the current candle. Relative Volume (RV) = current bar volume / 30-day average volume. If candle is bullish: positive volume → positive score. If candle is bearish: positive volume → negative score. If candle is doji/spinning top: sub-score = 0 regardless of RV.
A4: RV bucket | B4: Sub-score if BULLISH candle | C4: Sub-score if BEARISH candle | D4: Conviction interpretation | E4: Notes
A5: > 5.0× | B5: 100 | C5: -100 | D5: Extreme conviction | E5: Climactic — may also be exhaustion
A6: 3.0× – 5.0× | B6: 80 | C6: -80 | D6: Very strong
A7: 2.0× – 3.0× | B7: 60 | C7: -60 | D7: Strong
A8: 1.5× – 2.0× | B8: 40 | C8: -40 | D8: Above average
A9: 1.0× – 1.5× | B9: 20 | C9: -20 | D9: Slightly above avg
A10: 0.8× – 1.0× | B10: 0 | C10: 0 | D10: Normal — no signal
A11: 0.5× – 0.8× | B11: -15 | C11: 15 | D11: Weak conviction | E11: Move may not hold
A12: 0.3× – 0.5× | B12: -30 | C12: 30 | D12: Very weak
A13: 0.2× – 0.3× | B13: -40 | C13: 40 | D13: Suspicious
A14: < 0.2× | B14: -50 | C14: 50 | D14: No participation | E14: Move likely to fail

Sheet EMA
A1: EMA SYSTEM (weight: 15) — EMAs: 20, 50, 100, 200
A2: Two contributing signals: A) EMA stacking (position-based), B) Cross event (only on the cross bar). Final EMA sub-score = MAX(|stacking|, |cross|) preserving sign. This avoids double-counting.
A4: A. EMA Stacking | B4: Sub-score
A5: Price > EMA20 > EMA50 > EMA100 > EMA200 (full bull stack) | B5: 60
A6: Price above 3 of 4 EMAs | B6: 30
A7: Price above 2 of 4 EMAs (mixed) | B7: 0
A8: Price below 3 of 4 EMAs | B8: -30
A9: Price < EMA20 < EMA50 < EMA100 < EMA200 (full bear stack) | B9: -60
A12: B. Cross Event (fires only on cross bar) | B12: Sub-score
A13: Price crosses ABOVE EMA200 | B13: 95
A14: Price crosses ABOVE EMA100 | B14: 75
A15: Price crosses ABOVE EMA50 | B15: 55
A16: Price crosses ABOVE EMA20 | B16: 35
A17: Price crosses BELOW EMA20 | B17: -35
A18: Price crosses BELOW EMA50 | B18: -55
A19: Price crosses BELOW EMA100 | B19: -75
A20: Price crosses BELOW EMA200 | B20: -95

Sheet Support_Resistance
A1: SUPPORT / RESISTANCE (weight: 15)
A2: Default S/R identification: swing highs/lows from P5 pivot windows, clustered within 1% bands. Most recent unbroken cluster below price = support; above = resistance.
A4: Event | B4: Definition | C4: Sub-score | D4: Notes
A5: Strong bounce off support | B5: Close ≥ midpoint of bar range; range > avg range | C5: 80 | D5: High-conviction long signal
A6: Breakout above resistance | B6: Close above resistance with volume ≥ 1.5× avg | C6: 85 | D6: Trend continuation/breakout
A7: Approach support (no bounce yet) | B7: Bar touches support, no clear reaction | C7: 20 | D7: Watch for confirmation
A8: No interaction with key levels | B8: Price away from S/R | C8: 0 | D8: No level-based signal
A9: Approach resistance (no rejection yet) | B9: Bar touches resistance, no clear reaction | C9: -20 | D9: Watch for confirmation
A10: Strong rejection off resistance | B10: Close ≤ midpoint of bar range; range > avg | C10: -80 | D10: High-conviction short signal
A11: Breakdown below support | B11: Close below support with volume ≥ 1.5× avg | C11: -85 | D11: Trend continuation/breakdown

Sheet MACD
A1: MACD (weight: 18) — Standard 12/26/9
A2: Sum all triggered micro-signals on the current bar, then clip to [-100, +100]. Divergence is scored HERE (removed from RSI to avoid double-counting).
A4: Micro-signal | B4: Contribution | C4: Notes
A5: Golden cross (MACD line crosses signal up) on current bar | B5: 35 | C5: Bullish trigger
A6: MACD line above zero | B6: 15 | C6: Bullish bias
A7: Histogram: green and expanding (current > prior) | B7: 20 | C7: Strengthening bull momentum
A8: Histogram: green and contracting | B8: 5 | C8: Weakening bull momentum
A9: Bullish divergence (price LL, MACD HL) | B9: 30 | C9: Reversal warning (bullish)
A10: Bearish divergence (price HH, MACD LH) | B10: -30 | C10: Reversal warning (bearish)
A11: Histogram: red and contracting | B11: -5 | C11: Weakening bear momentum
A12: Histogram: red and expanding (more negative) | B12: -20 | C12: Strengthening bear momentum
A13: MACD line below zero | B13: -15 | C13: Bearish bias
A14: Death cross (MACD line crosses signal down) on current bar | B14: -35 | C14: Bearish trigger
A16: FINAL MACD SUB-SCORE = CLIP(sum of triggered signals, -100, +100)

Sheet RSI
A1: RSI (weight: 10) — Default RSI(14)
A2: Single sub-score per bar based on RSI zone and direction. Divergence handled in MACD — do not score here.
A4: Condition | B4: Sub-score | C4: Notes
A5: RSI crosses UP through 30 (exits oversold) | B5: 70 | C5: Strongest bullish trigger
A6: RSI < 30 and rising | B6: 40 | C6: Oversold reversal in progress
A7: RSI 30–50 and rising | B7: 25 | C7: Recovery
A8: RSI 50–70 and rising | B8: 25 | C8: Healthy bullish momentum
A9: RSI > 70 and rising | B9: 10 | C9: Strong but extended
A10: RSI < 30 and falling | B10: -10 | C10: Oversold deepening
A11: RSI 30–50 and falling | B11: -15 | C11: Weakening
A12: RSI 50–70 and falling | B12: -15 | C12: Bull momentum fading
A13: RSI > 70 and falling | B13: -40 | C13: Overbought rolling over
A14: RSI crosses DOWN through 70 (exits overbought) | B14: -70 | C14: Strongest bearish trigger

Sheet Example_Calc
A1: WORKED EXAMPLE — Composite Score Roll-up
A2: Edit the YELLOW sub-scores to see how the composite score changes. Weights are linked to Strategy_Config — edit there to change weights.
A4: Component | B4: Weight | C4: Sub-score (-100 to +100) | D4: Weighted (=B*C/100) | E4: Notes
A5: Candlestick pattern | B5: =Strategy_Config!C3 -> 12 | C5: 85 | D5: =B5*C5/100 -> 10.2 | E5: Green hammer at support
A6: P3 Pivot | B6: =Strategy_Config!C4 -> 8 | C6: 70 | D6: =B6*C6/100 -> 5.6 | E6: Bullish reversal at support
A7: P5 Pivot | B7: =Strategy_Config!C5 -> 12 | C7: 85 | D7: =B7*C7/100 -> 10.2 | E7: Major bullish reversal
A8: Volume (contextual) | B8: =Strategy_Config!C6 -> 10 | C8: 60 | D8: =B8*C8/100 -> 6 | E8: 2.5× avg on bullish candle
A9: EMA system | B9: =Strategy_Config!C7 -> 15 | C9: 35 | D9: =B9*C9/100 -> 5.25 | E9: Crossed above EMA20
A10: Support / Resistance | B10: =Strategy_Config!C8 -> 15 | C10: 80 | D10: =B10*C10/100 -> 12 | E10: Bounced off support
A11: MACD | B11: =Strategy_Config!C9 -> 18 | C11: 55 | D11: =B11*C11/100 -> 9.9 | E11: Golden cross + above zero + expanding green
A12: RSI | B12: =Strategy_Config!C10 -> 10 | C12: 40 | D12: =B12*C12/100 -> 4 | E12: RSI <30 and rising
A13: COMPOSITE SCORE | B13: =SUM(B5:B12) -> 100 | C13: (weight check) | D13: =SUM(D5:D12) -> 63.15
A14: SIGNAL | D14: =IF(D13>85,"STRONG BUY",IF(D13>=70,"BUY",IF(D13<=-85,"STRONG SELL",IF(D13<=-70,"SELL","HOLD")))) -> HOLD

Sheet Open_Questions
A1: OPEN QUESTIONS — must be resolved before going live
A2: # | B2: Question | C2: Default if unanswered | D2: Your decision (EDIT)
A3: 1 | B3: Asset universe? (US stocks, ASX, crypto?) | C3: US large/mid-cap, top 500 by liquidity
A4: 2 | B4: Timeframe — daily only, or multi-timeframe confirmation? | C4: Daily only for v1
A5: 3 | B5: Risk management: stop-loss method? | C5: 1.5 × ATR(14) below entry for longs
A6: 4 | B6: Position sizing method? | C6: 2% account risk per trade
A7: 5 | B7: Profit target / exit rule? | C7: Trail stop at 1.5 × ATR; exit on opposite signal
A8: 6 | B8: Max concurrent positions? | C8: 10
A9: 7 | B9: Re-entry rules after stop-out? | C9: Cooldown of 5 bars
A10: 8 | B10: Earnings / news blackout? | C10: Skip signals within 3 bars of earnings
A11: 9 | B11: Algorithmic S/R identification method? | C11: P5-swing + 1% clustering
A12: 10 | B12: Should weights/scores adapt to volatility regime? | C12: Static for v1; revisit after backtest
A13: 11 | B13: How to handle conflicting components (e.g., RSI overbought but EMA full bull stack)? | C13: Use composite — score will average out
A14: 12 | B14: Live data feed and broker integration? | C14: TBD — likely IBKR for execution; yfinance for v1 prototyping
A15: 13 | B15: What's the success metric for the strategy? | C15: Sharpe > 1.0 and max drawdown < 20% over 5-yr backtest
